{
  "top10": [
    { "slug": "Augustus", "rank": 1 },
    { "slug": "Constantine_the_Great", "rank": 2 },
    { "slug": "Diocletian", "rank": 3 },
    { "slug": "Trajan", "rank": 4 },
    { "slug": "Vespasian", "rank": 5 },
    { "slug": "Hadrian", "rank": 6 },
    { "slug": "Aurelian", "rank": 7 },
    { "slug": "Marcus_Aurelius", "rank": 8 },
    { "slug": "Septimius_Severus", "rank": 9 },
    { "slug": "Claudius", "rank": 10 }
  ],
  "bottom5": [
    { "slug": "Elagabalus", "rank": 5 },
    { "slug": "Nero", "rank": 3 },
    { "slug": "Commodus", "rank": 3 },
    { "slug": "Caracalla", "rank": 2 },
    { "slug": "Caligula", "rank": 1 }
  ]
}
